Metadata-Version: 2.1
Name: sqlite-utils-sqlite-path
Version: 0.2.1
Summary: TODO
Author: Alex Garcia
License: Apache-2.0
Project-URL: Homepage, https://github.com/asg017/sqlite-path
Project-URL: Changelog, https://github.com/asg017/sqlite-path/releases
Project-URL: Issues, https://github.com/asg017/sqlite-path/issues
Requires-Dist: sqlite-utils
Requires-Dist: sqlite-path
